ssmais/__init__.py
ssmais/manage.py
ssmais/provider/__init__.py
ssmais/provider/admin.py
ssmais/provider/apps.py
ssmais/provider/models.py
ssmais/provider/tests.py
ssmais/provider/views.py
ssmais/provider/migrations/0001_initial.py
ssmais/provider/migrations/__init__.py
ssmais/search/__init__.py
ssmais/search/admin.py
ssmais/search/apps.py
ssmais/search/forms.py
ssmais/search/models.py
ssmais/search/tests.py
ssmais/search/views.py
ssmais/search/migrations/__init__.py
ssmais/service/__init__.py
ssmais/service/admin.py
ssmais/service/apps.py
ssmais/service/forms.py
ssmais/service/models.py
ssmais/service/tests.py
ssmais/service/views.py
ssmais/service/migrations/0001_initial.py
ssmais/service/migrations/__init__.py
ssmais/ssmais/__init__.py
ssmais/ssmais/settings.py
ssmais/ssmais/urls.py
ssmais/ssmais/wsgi.py
ssmais/user/__init__.py
ssmais/user/admin.py
ssmais/user/apps.py
ssmais/user/constants.py
ssmais/user/forms.py
ssmais/user/models.py
ssmais/user/tests.py
ssmais/user/urls.py
ssmais/user/views.py
ssmais/user/migrations/__init__.py
ssmais-0.7.1.dist-info/DESCRIPTION.rst
ssmais-0.7.1.dist-info/METADATA
ssmais-0.7.1.dist-info/RECORD
ssmais-0.7.1.dist-info/WHEEL
ssmais-0.7.1.dist-info/metadata.json
ssmais-0.7.1.dist-info/top_level.txt
